Metadata-Version: 2.1
Name: demoji-lambda
Version: 0.4.0
Summary: Accurately remove and replace emojis in text strings
Home-page: https://github.com/tho-asterist/demoji
Author: Brad Solomon
Author-email: bsolomon@protonmail.com
License: Apache-2.0
Project-URL: Source, https://github.com/tho-asterist/demoji
Project-URL: Documentation, https://github.com/tho-asterist/demoji/blob/master/README.md
Project-URL: Bug Reports, https://github.com/tho-asterist/demoji/issues
Keywords: emoji,emojis,nlp,natural language processing,unicode
Platform: UNKNOWN
Classifier: Development Status :: 3 - Alpha
Classifier: Topic :: Utilities
Classifier: Topic :: Text Processing
Classifier: License :: OSI Approved :: Apache Software License
Classifier: Programming Language :: Python :: 3.7
Classifier: Programming Language :: Python :: 3.8
Classifier: Programming Language :: Python :: 3.9
Classifier: Programming Language :: Python :: Implementation :: CPython
Requires-Python: !=3.0.*,!=3.1.*,!=3.2.*,!=3.3.*,!=3.4.*,>=2.7
